LICENSE.txt
README.md
thunder/__init__.py
thunder/blocks.py
thunder/callbacks.py
thunder/citrinet/__init__.py
thunder/citrinet/blocks.py
thunder/citrinet/compatibility.py
thunder/ctc_loss.py
thunder/data/__init__.py
thunder/data/dataloader_utils.py
thunder/data/datamodule.py
thunder/data/dataset.py
thunder/finetune.py
thunder/huggingface/__init__.py
thunder/huggingface/compatibility.py
thunder/huggingface/transform.py
thunder/module.py
thunder/quartznet/__init__.py
thunder/quartznet/blocks.py
thunder/quartznet/compatibility.py
thunder/quartznet/spec_augment.py
thunder/quartznet/transform.py
thunder/registry.py
thunder/text_processing/__init__.py
thunder/text_processing/preprocess.py
thunder/text_processing/tokenizer.py
thunder/text_processing/transform.py
thunder/text_processing/vocab.py
thunder/utils.py
thunder_speech-3.2.0.dist-info/LICENSE.txt
thunder_speech-3.2.0.dist-info/WHEEL
thunder_speech-3.2.0.dist-info/METADATA
thunder_speech-3.2.0.dist-info/RECORD
