Metadata-Version: 2.1
Name: thunder-speech
Version: 3.2.0
Summary: A Hackable speech recognition library
Home-page: https://scart97.github.io/thunder-speech/
License: MIT
Keywords: python,pytorch,speech recognition
Author: scart97
Author-email: scart.lucas@gmail.com
Requires-Python: >=3.8,<4.0
Classifier: License :: OSI Approved :: MIT License
Classifier: Programming Language :: Python :: 3
Classifier: Programming Language :: Python :: 3.10
Classifier: Programming Language :: Python :: 3.8
Classifier: Programming Language :: Python :: 3.9
Requires-Dist: editdistance (>=0.6.0,<0.7.0)
Requires-Dist: hydra-core (>=1.1.2,<2.0.0)
Requires-Dist: importlib-metadata (>=4.12.0,<5.0.0)
Requires-Dist: num2words (>=0.5.10,<0.6.0)
Requires-Dist: protobuf (==3.18.1)
Requires-Dist: pytorch-lightning (>=1.7.0,<2.0.0)
Requires-Dist: sentencepiece (>=0.1.96,<0.2.0)
Requires-Dist: torch (>=1.12,<2.0)
Requires-Dist: torchaudio (>=0.12,<0.13)
Requires-Dist: torchmetrics (>=0.8,<0.10)
Requires-Dist: transformers (>=4.20.1,<5.0.0)
Requires-Dist: wget (>=3.2,<4.0)
Project-URL: Documentation, https://scart97.github.io/thunder-speech/
Project-URL: Repository, https://github.com/scart97/thunder-speech
